WebSearcher/__init__.py
WebSearcher/component_classifier.py
WebSearcher/locations.py
WebSearcher/logger.py
WebSearcher/parsers.py
WebSearcher/searchers.py
WebSearcher/utils.py
WebSearcher/webutils.py
WebSearcher/component_parsers/__init__.py
WebSearcher/component_parsers/ads.py
WebSearcher/component_parsers/available_on.py
WebSearcher/component_parsers/footer.py
WebSearcher/component_parsers/general.py
WebSearcher/component_parsers/images.py
WebSearcher/component_parsers/knowledge.py
WebSearcher/component_parsers/latest_from.py
WebSearcher/component_parsers/local_results.py
WebSearcher/component_parsers/map_results.py
WebSearcher/component_parsers/news_quotes.py
WebSearcher/component_parsers/people_also_ask.py
WebSearcher/component_parsers/top_stories.py
WebSearcher/component_parsers/twitter_cards.py
WebSearcher/component_parsers/twitter_result.py
WebSearcher/component_parsers/videos.py
WebSearcher/component_parsers/view_more_news.py
WebSearching-0.1.7.dist-info/LICENSE
WebSearching-0.1.7.dist-info/METADATA
WebSearching-0.1.7.dist-info/WHEEL
WebSearching-0.1.7.dist-info/top_level.txt
WebSearching-0.1.7.dist-info/RECORD
